[
    {
        "domain": ".facebook.com",
        "expirationDate": 1743203263.388743,
        "hostOnly": false,
        "httpOnly": true,
        "name": "ps_l",
        "path": "/",
        "sameSite": "lax",
        "secure": true,
        "session": false,
        "storeId": null,
        "value": "0"
    },
    {
        "domain": ".facebook.com",
        "expirationDate": 1740210345,
        "hostOnly": false,
        "httpOnly": false,
        "name": "fbl_ci",
        "path": "/",
        "sameSite": "no_restriction",
        "secure": true,
        "session": false,
        "storeId": null,
        "value": "7206281916127670"
    },
    {
        "domain": ".facebook.com",
        "expirationDate": 1716450340.934653,
        "hostOnly": false,
        "httpOnly": true,
        "name": "fr",
        "path": "/",
        "sameSite": "no_restriction",
        "secure": true,
        "session": false,
        "storeId": null,
        "value": "0UP3on3GzG8eGQCIq.AWWjdQNJIIrmxm87wU4Yg8if3bU.Bl19O-..AAA.0.0.Bl2E0k.AWU1Pxm47-E"
    },
    {
        "domain": ".facebook.com",
        "expirationDate": 1713858345,
        "hostOnly": false,
        "httpOnly": false,
        "name": "vpd",
        "path": "/",
        "sameSite": "lax",
        "secure": true,
        "session": false,
        "storeId": null,
        "value": "v1%3B785x412x1.75"
    },
    {
        "domain": ".facebook.com",
        "expirationDate": 1740199914.137856,
        "hostOnly": false,
        "httpOnly": true,
        "name": "xs",
        "path": "/",
        "sameSite": "no_restriction",
        "secure": true,
        "session": false,
        "storeId": null,
        "value": "41%3AXJQdWBLY5VcQqA%3A2%3A1708663911%3A-1%3A-1"
    },
    {
        "domain": ".facebook.com",
        "expirationDate": 1740210345,
        "hostOnly": false,
        "httpOnly": false,
        "name": "fbl_st",
        "path": "/",
        "sameSite": "strict",
        "secure": true,
        "session": false,
        "storeId": null,
        "value": "101221981%3BT%3A28477905"
    },
    {
        "domain": ".facebook.com",
        "expirationDate": 1709248708.02368,
        "hostOnly": false,
        "httpOnly": false,
        "name": "locale",
        "path": "/",
        "sameSite": "no_restriction",
        "secure": true,
        "session": false,
        "storeId": null,
        "value": "en_US"
    },
    {
        "domain": ".facebook.com",
        "expirationDate": 1740199914.137296,
        "hostOnly": false,
        "httpOnly": false,
        "name": "c_user",
        "path": "/",
        "sameSite": "no_restriction",
        "secure": true,
        "session": false,
        "storeId": null,
        "value": "61556664632787"
    },
    {
        "domain": ".facebook.com",
        "hostOnly": false,
        "httpOnly": false,
        "name": "",
        "path": "/",
        "sameSite": null,
        "secure": false,
        "session": true,
        "storeId": null,
        "value": "0tCm83SXUgvPiiaKo.AWUH4zzMpiJa3X8YtnvyBLo5VcI.BkEFsO.B3.AAA.0.0.BkEFsO.AWV6DEolPeU"
    },
    {
        "domain": ".facebook.com",
        "expirationDate": 1740210345,
        "hostOnly": false,
        "httpOnly": false,
        "name": "fbl_cs",
        "path": "/",
        "sameSite": "no_restriction",
        "secure": true,
        "session": false,
        "storeId": null,
        "value": "AhDcQXrRM6vMFA7rlpr4gwRPGFpOblVJNXNUTkN2L05jS2doWDI2ZTRKag"
    },
    {
        "domain": ".facebook.com",
        "expirationDate": 1716439914.943813,
        "hostOnly": false,
        "httpOnly": true,
        "name": "m_page_voice",
        "path": "/",
        "sameSite": "no_restriction",
        "secure": true,
        "session": false,
        "storeId": null,
        "value": "61556664632787"
    },
    {
        "domain": ".facebook.com",
        "expirationDate": 1743203263.388942,
        "hostOnly": false,
        "httpOnly": true,
        "name": "ps_n",
        "path": "/",
        "sameSite": "no_restriction",
        "secure": true,
        "session": false,
        "storeId": null,
        "value": "0"
    },
    {
        "domain": ".facebook.com",
        "expirationDate": 1743223914.136843,
        "hostOnly": false,
        "httpOnly": true,
        "name": "sb",
        "path": "/",
        "sameSite": "no_restriction",
        "secure": true,
        "session": false,
        "storeId": null,
        "value": "vtPXZfylfWFzVvRECCL9MoKy"
    },
    {
        "domain": ".facebook.com",
        "expirationDate": 1709268734,
        "hostOnly": false,
        "httpOnly": false,
        "name": "wd",
        "path": "/",
        "sameSite": "lax",
        "secure": true,
        "session": false,
        "storeId": null,
        "value": "412x785"
    },
    {
        "domain": ".facebook.com",
        "expirationDate": 1716420680,
        "hostOnly": false,
        "httpOnly": false,
        "name": "wl_cbv",
        "path": "/",
        "sameSite": "no_restriction",
        "secure": true,
        "session": false,
        "storeId": null,
        "value": "v2%3Bclient_version%3A2416%3Btimestamp%3A1708644679"
    }
]
